simple_dyn365/__init__.py
simple_dyn365/api.py
simple_dyn365/login.py
simple_dyn365-1.6.1.dist-info/LICENSE
simple_dyn365-1.6.1.dist-info/METADATA
simple_dyn365-1.6.1.dist-info/WHEEL
simple_dyn365-1.6.1.dist-info/top_level.txt
simple_dyn365-1.6.1.dist-info/RECORD
